Pipfile
README.rst
requirements.txt
setup.py
pynndb_shell/__init__.py
pynndb_shell.egg-info/PKG-INFO
pynndb_shell.egg-info/SOURCES.txt
pynndb_shell.egg-info/dependency_links.txt
pynndb_shell.egg-info/entry_points.txt
pynndb_shell.egg-info/requires.txt
pynndb_shell.egg-info/top_level.txt