Metadata-Version: 1.1
Name: pynndb-shell
Version: 1.0.9
Summary: Database library for Python based on LMDB storage engine
Home-page: https://github.com/oddjobz/pynndb-shell
Author: Gareth Bult
Author-email: oddjobz@linux.co.uk
License: MIT
Keywords: pynndb,cli,shell,python,database
Platform: UNKNOWN
Classifier: Development Status :: 3 - Alpha
Classifier: Intended Audience :: Developers
Classifier: Topic :: Database :: Database Engines/Servers
Classifier: License :: OSI Approved :: MIT License
Classifier: Programming Language :: Python :: 3.6
